adagio/__init__.py
adagio/exceptions.py
adagio/instances.py
adagio/specs.py
adagio/shells/__init__.py
adagio/shells/interfaceless.py
adagio_version/__init__.py
tests/shells/__init__.py
tests/shells/test_interfaceless.py
adagio-0.2.6.dist-info/LICENSE
adagio-0.2.6.dist-info/METADATA
adagio-0.2.6.dist-info/WHEEL
adagio-0.2.6.dist-info/top_level.txt
adagio-0.2.6.dist-info/RECORD
