Metadata-Version: 2.1
Name: adagio
Version: 0.2.6
Summary: The Dag IO Framework for Fugue projects
Home-page: http://github.com/fugue-project/adagio
Author: Han Wang
Author-email: goodwanghan@gmail.com
License: Apache-2.0
Keywords: adagio dag directed acyclic graph workflow
Classifier: Development Status :: 3 - Alpha
Classifier: Intended Audience :: Developers
Classifier: Topic :: Software Development :: Libraries :: Python Modules
Classifier: License :: OSI Approved :: Apache Software License
Classifier: Programming Language :: Python :: 3
Classifier: Programming Language :: Python :: 3.8
Classifier: Programming Language :: Python :: 3.9
Classifier: Programming Language :: Python :: 3.10
Classifier: Programming Language :: Python :: 3.11
Classifier: Programming Language :: Python :: 3.12
Classifier: Programming Language :: Python :: 3 :: Only
Requires-Python: >=3.8
License-File: LICENSE
